MANIFEST.in
README.txt
setup.py
couchexport/__init__.py
couchexport/export.py
couchexport/models.py
couchexport/urls.py
couchexport/views.py
couchexport.egg-info/PKG-INFO
couchexport.egg-info/SOURCES.txt
couchexport.egg-info/dependency_links.txt
couchexport.egg-info/requires.txt
couchexport.egg-info/top_level.txt
couchexport/_design/util/reconcile.js
couchexport/_design/util/schema.js
couchexport/_design/views/schema/map.js
couchexport/_design/views/schema/reduce.js
couchexport/_design/views/schema_index/map.js