Metadata-Version: 1.0
Name: couchexport
Version: 0.0.1.2
Summary: Dimagi Couch Exporter for Django
Home-page: http://www.dimagi.com/
Author: Dimagi
Author-email: information@dimagi.com
License: UNKNOWN
Platform: UNKNOWN
